LICENSE.txt
MANIFEST.in
README.rst
setup.cfg
setup.py
oxitopped/__init__.py
oxitopped/bottles.py
oxitopped/daemon.py
oxitopped/example.xml
oxitopped/export_csv.py
oxitopped/export_xls.py
oxitopped/logger.py
oxitopped/nullmodem.py
oxitopped/oxitopdump.py
oxitopped/oxitopemu.py
oxitopped/oxitoplist.py
oxitopped/oxitopview.py
oxitopped/patches.py
oxitopped/terminal.py
oxitopped.egg-info/PKG-INFO
oxitopped.egg-info/SOURCES.txt
oxitopped.egg-info/dependency_links.txt
oxitopped.egg-info/entry_points.txt
oxitopped.egg-info/requires.txt
oxitopped.egg-info/top_level.txt
oxitopped.egg-info/zip-safe
oxitopped/windows/__init__.py
oxitopped/windows/bottle_window.py
oxitopped/windows/bottle_window.ui
oxitopped/windows/connect_dialog.py
oxitopped/windows/connect_dialog.ui
oxitopped/windows/data_logger_window.py
oxitopped/windows/data_logger_window.ui
oxitopped/windows/export_csv_dialog.py
oxitopped/windows/export_csv_dialog.ui
oxitopped/windows/export_excel_dialog.py
oxitopped/windows/export_excel_dialog.ui
oxitopped/windows/exporter.py
oxitopped/windows/main_window.py
oxitopped/windows/main_window.ui
oxitopped/windows/fallback-theme/application-exit.png
oxitopped/windows/fallback-theme/application-exit.svg
oxitopped/windows/fallback-theme/document-open.png
oxitopped/windows/fallback-theme/document-open.svg
oxitopped/windows/fallback-theme/image-x-generic.png
oxitopped/windows/fallback-theme/image-x-generic.svg
oxitopped/windows/fallback-theme/text-x-generic.png
oxitopped/windows/fallback-theme/text-x-generic.svg
oxitopped/windows/fallback-theme/view-refresh.png
oxitopped/windows/fallback-theme/view-refresh.svg
oxitopped/windows/fallback-theme/x-office-document.png
oxitopped/windows/fallback-theme/x-office-document.svg