Metadata-Version: 1.1
Name: oxitopped
Version: 0.2
Summary: Tools for extracting data from an OxiTop OC110 data logger
Home-page: https://www.waveform.org.uk/oxitopped/
Author: Dave Hughes
Author-email: dave@waveform.org.uk
License: UNKNOWN
Keywords: science gas bottle oxitop
Platform: ALL
Classifier: Development Status :: 4 - Beta
Classifier: Environment :: Console
Classifier: Environment :: Win32 (MS Windows)
Classifier: Environment :: X11 Applications :: Qt
Classifier: Intended Audience :: Science/Research
Classifier: License :: OSI Approved :: GNU General Public License v3 or later (GPLv3+)
Classifier: Operating System :: Microsoft :: Windows
Classifier: Operating System :: POSIX
Classifier: Operating System :: Unix
Classifier: Programming Language :: Python :: 2.6
Classifier: Programming Language :: Python :: 2.7
Classifier: Topic :: Scientific/Engineering
